{"cameraMode":{"drawMode":0,"name":"Shaded","section":"Shading Mode"},"sceneLighting":true,"audioPlay":false,"sceneViewState":{"m_AlwaysRefresh":false,"showFog":true,"showSkybox":true,"showFlares":true,"showImageEffects":true,"showParticleSystems":true,"showVisualEffectGraphs":true,"m_FxEnabled":true},"in2DMode":false,"pivot":{"x":-0.5412300229072571,"y":8.1899995803833,"z":-9.777099609375},"rotation":{"x":0.09522445499897003,"y":0.9005933403968811,"z":-0.2507011890411377,"w":0.34207412600517275},"size":10.0,"orthographic":false}